package/__init__.py
package/scripts.py
india_cities_pincode-1.0.1.dist-info/LICENSE
india_cities_pincode-1.0.1.dist-info/METADATA
india_cities_pincode-1.0.1.dist-info/WHEEL
india_cities_pincode-1.0.1.dist-info/top_level.txt
india_cities_pincode-1.0.1.dist-info/RECORD
