Metadata-Version: 2.1
Name: india-cities-pincode
Version: 1.0.1
Summary: this package use for get all india cities pincode
Home-page: UNKNOWN
Author: Vikash
Author-email: vikashminj1999@gmail.com
License: UNKNOWN
Platform: UNKNOWN
Classifier: Intended Audience :: Developers
Classifier: License :: OSI Approved :: MIT License
Classifier: Programming Language :: Python :: 3
Classifier: Programming Language :: Python :: 3.7
Classifier: Programming Language :: Python :: 3.8
Classifier: Programming Language :: Python :: 3.9
License-File: LICENSE
